extraxt/__init__.py
extraxt/module/__init__.py
extraxt/module/formatter/__init__.py
extraxt/module/parser/__init__.py
extraxt/util/__init__.py
extraxt-0.0.18.dist-info/LICENSE
extraxt-0.0.18.dist-info/METADATA
extraxt-0.0.18.dist-info/WHEEL
extraxt-0.0.18.dist-info/top_level.txt
extraxt-0.0.18.dist-info/RECORD
