Metadata-Version: 2.2
Name: extraxt
Version: 0.0.18
Summary: Easily extract data from PDFs.
Home-page: https://github.com/samsa-eng/extraxt
Author: Matt J. Stevenson
Author-email: dev@mattjs.me
Classifier: Programming Language :: Python :: 3
Classifier: License :: OSI Approved :: MIT License
Classifier: Operating System :: OS Independent
Requires-Python: >=3.11
License-File: LICENSE
Requires-Dist: pandas
Requires-Dist: PyMuPDF
Dynamic: author
Dynamic: author-email
Dynamic: classifier
Dynamic: description
Dynamic: description-content-type
Dynamic: home-page
Dynamic: requires-dist
Dynamic: requires-python
Dynamic: summary
